uEagle/__init__.py
uEagle/uEagle.py
uEagle-0.0.2.dist-info/LICENSE
uEagle-0.0.2.dist-info/METADATA
uEagle-0.0.2.dist-info/WHEEL
uEagle-0.0.2.dist-info/top_level.txt
uEagle-0.0.2.dist-info/RECORD
