Metadata-Version: 2.1
Name: uEagle
Version: 0.0.2
Summary: Tool to read data from Rainforest Legacy Eagle.
Home-page: https://github.com/jcalbert/uEagle
Author: Joseph Albert
Author-email: joe@jcalbert.com
License: UNKNOWN
Keywords: rainforest eagle
Platform: UNKNOWN
Classifier: Development Status :: 4 - Beta
Classifier: Programming Language :: Python :: Implementation :: CPython
Classifier: Topic :: Home Automation
Requires-Python: >=3
Requires-Dist: requests
